AUTHORS
CHANGELOG
LICENSE
MANIFEST.in
README.rst
pyproject.toml
setup.py
django_impersonate.egg-info/PKG-INFO
django_impersonate.egg-info/SOURCES.txt
django_impersonate.egg-info/dependency_links.txt
django_impersonate.egg-info/top_level.txt
impersonate/__init__.py
impersonate/admin.py
impersonate/apps.py
impersonate/compat.py
impersonate/decorators.py
impersonate/helpers.py
impersonate/middleware.py
impersonate/models.py
impersonate/settings.py
impersonate/signals.py
impersonate/tests.py
impersonate/urls.py
impersonate/views.py
impersonate/migrations/0001_initial.py
impersonate/migrations/__init__.py
impersonate/templates/impersonate/list_users.html
impersonate/templates/impersonate/search_users.html